{
  "timestamp_utc": "2025-11-11T15:20:02Z",
  "hours_back": 6,
  "step_min": 12,
  "detectors": {
    "C2": {
      "frames": 30,
      "tracks": 70,
      "last_frame_name": "C2_20251111_0736_c2_1024.jpg",
      "last_frame_iso": "2025-11-11T07:36:00Z",
      "last_frame_size": [
        1024,
        1024
      ]
    },
    "C3": {
      "frames": 30,
      "tracks": 1014,
      "last_frame_name": "C3_20251111_0742_c3_1024.jpg",
      "last_frame_iso": "2025-11-11T07:42:00Z",
      "last_frame_size": [
        1024,
        1024
      ]
    }
  },
  "fetched_new_frames": 60,
  "errors": [],
  "auto_selected_count": 811,
  "candidates_in_report": 1084,
  "name": "latest_status.json",
  "generated_at": "2025-11-11T15:20:02Z"
}