{
  "timestamp_utc": "2025-11-10T21:41:14Z",
  "hours_back": 6,
  "step_min": 12,
  "detectors": {
    "C2": {
      "frames": 30,
      "tracks": 138,
      "last_frame_name": "C2_20251110_1336_c2_1024.jpg",
      "last_frame_iso": "2025-11-10T13:36:00Z",
      "last_frame_size": [
        1024,
        1024
      ]
    },
    "C3": {
      "frames": 30,
      "tracks": 926,
      "last_frame_name": "C3_20251110_1342_c3_1024.jpg",
      "last_frame_iso": "2025-11-10T13:42:00Z",
      "last_frame_size": [
        1024,
        1024
      ]
    }
  },
  "fetched_new_frames": 60,
  "errors": [],
  "auto_selected_count": 541,
  "candidates_in_report": 1064,
  "name": "latest_status.json",
  "generated_at": "2025-11-10T21:41:14Z"
}